{
  "symbol": "COCHINSHIP",
  "url": "https://www.screener.in/company/COCHINSHIP/consolidated/",
  "timestamp": 1743771486.20892,
  "quarterly_results": {
    "date": [
      "Dec 2021",
      "Mar 2022",
      "Jun 2022",
      "Sep 2022",
      "Dec 2022",
      "Mar 2023",
      "Jun 2023",
      "Sep 2023",
      "Dec 2023",
      "Mar 2024",
      "Jun 2024",
      "Sep 2024",
      "Dec 2024"
    ],
    "Sales\u00a0+": [
      953,
      1212,
      441,
      683,
      642,
      600,
      476,
      1012,
      1056,
      1286,
      771,
      1143,
      1148
    ],
    "Expenses\u00a0+": [
      812,
      916,
      409,
      548,
      493,
      667,
      397,
      821,
      746,
      998,
      594,
      946,
      910
    ],
    "Operating Profit": [
      141,
      296,
      32,
      135,
      148,
      -67,
      79,
      191,
      310,
      288,
      177,
      197,
      237
    ],
    "OPM %": [
      15,
      24,
      7,
      20,
      23,
      -11,
      17,
      19,
      29,
      22,
      23,
      17,
      21
    ],
    "Other Income\u00a0+": [
      63,
      107,
      56,
      62,
      23,
      133,
      84,
      89,
      58,
      80,
      84,
      101,
      47
    ],
    "Interest": [
      12,
      12,
      12,
      12,
      12,
      -1,
      9,
      10,
      8,
      7,
      7,
      9,
      11
    ],
    "Depreciation": [
      18,
      18,
      19,
      20,
      19,
      11,
      17,
      19,
      20,
      19,
      19,
      26,
      32
    ],
    "Profit before tax": [
      175,
      374,
      56,
      165,
      140,
      57,
      137,
      251,
      340,
      342,
      236,
      263,
      242
    ],
    "Tax %": [
      26,
      27,
      25,
      32,
      21,
      30,
      28,
      28,
      28,
      24,
      26,
      28,
      27
    ],
    "Net Profit\u00a0+": [
      129,
      275,
      42,
      113,
      110,
      39,
      99,
      182,
      244,
      259,
      174,
      189,
      177
    ],
    "EPS in Rs": [
      4.92,
      10.44,
      1.6,
      4.29,
      4.2,
      1.5,
      3.75,
      6.9,
      9.29,
      9.84,
      6.62,
      7.18,
      6.73
    ],
    "Raw PDF": [
      0,
      0,
      0,
      0,
      0,
      0,
      0,
      0,
      0,
      0,
      0,
      0,
      0
    ]
  },
  "profit_loss": {
    "date": [
      "Mar 2018",
      "Mar 2019",
      "Mar 2020",
      "Mar 2021",
      "Mar 2022",
      "Mar 2023",
      "Mar 2024",
      "TTM"
    ],
    "Sales\u00a0+": [
      2355,
      2966,
      3422,
      2819,
      3191,
      2365,
      3830,
      4348
    ],
    "Expenses\u00a0+": [
      1891,
      2394,
      2711,
      2096,
      2564,
      2103,
      2949,
      3448
    ],
    "Operating Profit": [
      465,
      571,
      711,
      723,
      627,
      262,
      882,
      900
    ],
    "OPM %": [
      20,
      19,
      21,
      26,
      20,
      11,
      23,
      21
    ],
    "Other Income\u00a0+": [
      189,
      226,
      245,
      203,
      260,
      269,
      310,
      312
    ],
    "Interest": [
      12,
      15,
      50,
      58,
      53,
      43,
      46,
      33
    ],
    "Depreciation": [
      38,
      34,
      49,
      60,
      68,
      69,
      75,
      96
    ],
    "Profit before tax": [
      604,
      748,
      858,
      808,
      766,
      418,
      1071,
      1083
    ],
    "Tax %": [
      34,
      36,
      26,
      25,
      26,
      27,
      27,
      0
    ],
    "Net Profit\u00a0+": [
      396,
      478,
      632,
      609,
      564,
      305,
      783,
      799
    ],
    "EPS in Rs": [
      14.58,
      18.17,
      24.02,
      23.13,
      21.44,
      11.58,
      29.77,
      30.37
    ],
    "Dividend Payout %": [
      41,
      36,
      35,
      34,
      39,
      73,
      33,
      0
    ]
  },
  "compounded_sales_growth": {
    "date": [
      "5 Years",
      "3 Years",
      "1 Years",
      "TTM",
      "Last Year"
    ],
    "Compounded Sales Growth": [
      14.0,
      12.0,
      30.0,
      38.0,
      17.0
    ]
  },
  "compounded_profit_growth": {
    "date": [
      "5 Years",
      "3 Years",
      "1 Years",
      "TTM",
      "Last Year"
    ],
    "Compounded Profit Growth": [
      14.0,
      12.0,
      30.0,
      38.0,
      17.0
    ]
  },
  "stock_price_cagr": {
    "date": [
      "5 Years",
      "3 Years",
      "1 Years",
      "TTM",
      "Last Year"
    ],
    "Stock Price Cagr": [
      14.0,
      12.0,
      30.0,
      38.0,
      17.0
    ]
  },
  "return_on_equity": {
    "date": [
      "5 Years",
      "3 Years",
      "1 Years",
      "TTM",
      "Last Year"
    ],
    "Return On Equity": [
      14.0,
      12.0,
      30.0,
      38.0,
      17.0
    ]
  },
  "balance_sheet": {
    "date": [
      "Mar 2018",
      "Mar 2019",
      "Mar 2020",
      "Mar 2021",
      "Mar 2022",
      "Mar 2023",
      "Mar 2024",
      "Sep 2024"
    ],
    "Equity Capital": [
      136,
      132,
      132,
      132,
      132,
      132,
      132,
      132
    ],
    "Reserves": [
      3120,
      3197,
      3591,
      3902,
      4262,
      4296,
      4872,
      5144
    ],
    "Borrowings\u00a0+": [
      123,
      123,
      123,
      540,
      554,
      587,
      502,
      501
    ],
    "Other Liabilities\u00a0+": [
      2109,
      1799,
      2565,
      2976,
      3467,
      5006,
      6531,
      6618
    ],
    "Total Liabilities": [
      5487,
      5251,
      6411,
      7549,
      8414,
      10021,
      12037,
      12395
    ],
    "Fixed Assets\u00a0+": [
      349,
      376,
      764,
      867,
      970,
      953,
      968,
      1702
    ],
    "CWIP": [
      121,
      342,
      799,
      1176,
      1264,
      1619,
      2196,
      1719
    ],
    "Investments": [
      0,
      0,
      0,
      0,
      0,
      0,
      0,
      0
    ],
    "Other Assets\u00a0+": [
      5017,
      4532,
      4848,
      5506,
      6180,
      7449,
      8873,
      8974
    ],
    "Total Assets": [
      5487,
      5251,
      6411,
      7549,
      8414,
      10021,
      12037,
      12395
    ]
  },
  "cash_flows": {
    "date": [
      "Mar 2018",
      "Mar 2019",
      "Mar 2020",
      "Mar 2021",
      "Mar 2022",
      "Mar 2023",
      "Mar 2024"
    ],
    "Debtor Days": [
      90,
      48,
      31,
      46,
      50,
      52,
      34
    ],
    "Inventory Days": [
      98,
      70,
      65,
      139,
      67,
      122,
      216
    ],
    "Days Payable": [
      83,
      84,
      85,
      130,
      38,
      71,
      98
    ],
    "Cash Conversion Cycle": [
      104,
      34,
      10,
      54,
      79,
      103,
      152
    ],
    "Working Capital Days": [
      -114,
      -27,
      9,
      -5,
      -92,
      -399,
      -163
    ],
    "ROCE %": [
      0,
      22,
      25,
      20,
      17,
      8,
      21
    ]
  },
  "ratios": {
    "date": [
      "Mar 2018",
      "Mar 2019",
      "Mar 2020",
      "Mar 2021",
      "Mar 2022",
      "Mar 2023",
      "Mar 2024"
    ],
    "Debtor Days": [
      90,
      48,
      31,
      46,
      50,
      52,
      34
    ],
    "Inventory Days": [
      98,
      70,
      65,
      139,
      67,
      122,
      216
    ],
    "Days Payable": [
      83,
      84,
      85,
      130,
      38,
      71,
      98
    ],
    "Cash Conversion Cycle": [
      104,
      34,
      10,
      54,
      79,
      103,
      152
    ],
    "Working Capital Days": [
      -114,
      -27,
      9,
      -5,
      -92,
      -399,
      -163
    ],
    "ROCE %": [
      0,
      22,
      25,
      20,
      17,
      8,
      21
    ]
  },
  "shareholding_pattern": {
    "date": [
      "Mar 2022",
      "Jun 2022",
      "Sep 2022",
      "Dec 2022",
      "Mar 2023",
      "Jun 2023",
      "Sep 2023",
      "Dec 2023",
      "Mar 2024",
      "Jun 2024",
      "Sep 2024",
      "Dec 2024"
    ],
    "Promoters\u00a0+": [
      72.86,
      72.86,
      72.86,
      72.86,
      72.86,
      72.86,
      72.86,
      72.86,
      72.86,
      72.86,
      72.86,
      67.91
    ],
    "FIIs\u00a0+": [
      2.73,
      2.75,
      3.68,
      6.87,
      6.28,
      5.73,
      5.82,
      4.11,
      5.23,
      4.94,
      3.84,
      2.91
    ],
    "DIIs\u00a0+": [
      4.29,
      4.37,
      4.96,
      3.87,
      3.78,
      3.21,
      2.24,
      2.2,
      2.45,
      2.5,
      3.0,
      6.63
    ],
    "Public\u00a0+": [
      20.12,
      20.02,
      18.48,
      16.39,
      17.07,
      18.19,
      19.07,
      20.84,
      19.47,
      19.71,
      20.31,
      22.54
    ],
    "No. of Shareholders": [
      171090,
      170100,
      164504,
      169257,
      169264,
      180979,
      266437,
      292212,
      396327,
      634075,
      841968,
      981567
    ]
  },
  "market_data": {
    "Market Cap": 36559,
    "Current Price": 1391,
    "High / Low": "2979 / 1024",
    "Stock P/E": 45.8,
    "Book Value": 201,
    "Dividend Yield": 0.7,
    "ROCE": 21.2,
    "ROE": 16.6,
    "Face Value": 5.0
  },
  "remarks": {
    "pros": [
      "Company is almost debt free.",
      "Company is expected to give good quarter",
      "Company has been maintaining a healthy dividend payout of 48.4%",
      "Debtor days have improved from 45.4 to 33.9 days."
    ],
    "cons": [
      "Promoter holding has decreased over last quarter: -4.95%",
      "The company has delivered a poor sales growth of 5.25% over past five years.",
      "Company has a low return on equity of 12.1% over last 3 years.",
      "Earnings include an other income of Rs.312 Cr."
    ]
  }
}