{
  "symbol": "MAPMYINDIA",
  "url": "https://www.screener.in/company/MAPMYINDIA/consolidated/",
  "timestamp": 1743770941.181043,
  "quarterly_results": {
    "date": [
      "Dec 2021",
      "Mar 2022",
      "Jun 2022",
      "Sep 2022",
      "Dec 2022",
      "Mar 2023",
      "Jun 2023",
      "Sep 2023",
      "Dec 2023",
      "Mar 2024",
      "Jun 2024",
      "Sep 2024",
      "Dec 2024"
    ],
    "Sales\u00a0+": [
      43,
      57,
      65,
      76,
      68,
      72,
      89,
      91,
      92,
      107,
      101,
      104,
      115
    ],
    "Expenses\u00a0+": [
      28,
      32,
      35,
      46,
      40,
      44,
      52,
      51,
      57,
      67,
      59,
      67,
      73
    ],
    "Operating Profit": [
      16,
      25,
      30,
      30,
      28,
      29,
      37,
      40,
      35,
      40,
      42,
      37,
      41
    ],
    "OPM %": [
      36,
      44,
      46,
      40,
      41,
      40,
      42,
      44,
      38,
      37,
      42,
      36,
      36
    ],
    "Other Income\u00a0+": [
      9,
      12,
      6,
      8,
      11,
      10,
      8,
      8,
      12,
      12,
      10,
      10,
      9
    ],
    "Interest": [
      0,
      1,
      1,
      1,
      1,
      1,
      1,
      1,
      1,
      1,
      1,
      1,
      1
    ],
    "Depreciation": [
      2,
      2,
      2,
      2,
      2,
      4,
      3,
      4,
      4,
      4,
      5,
      6,
      5
    ],
    "Profit before tax": [
      22,
      34,
      34,
      36,
      36,
      34,
      42,
      44,
      42,
      47,
      47,
      41,
      44
    ],
    "Tax %": [
      15,
      33,
      28,
      29,
      17,
      18,
      24,
      25,
      26,
      19,
      24,
      25,
      27
    ],
    "Net Profit\u00a0+": [
      19,
      23,
      24,
      25,
      30,
      28,
      32,
      33,
      31,
      38,
      36,
      30,
      32
    ],
    "EPS in Rs": [
      3.48,
      4.23,
      4.54,
      4.74,
      5.52,
      5.22,
      6.0,
      6.11,
      5.69,
      7.02,
      6.62,
      5.58,
      5.96
    ],
    "Raw PDF": [
      0,
      0,
      0,
      0,
      0,
      0,
      0,
      0,
      0,
      0,
      0,
      0,
      0
    ]
  },
  "profit_loss": {
    "date": [
      "Mar 2019",
      "Mar 2020",
      "Mar 2021",
      "Mar 2022",
      "Mar 2023",
      "Mar 2024",
      "TTM"
    ],
    "Sales\u00a0+": [
      135,
      149,
      152,
      200,
      281,
      379,
      427
    ],
    "Expenses\u00a0+": [
      110,
      119,
      101,
      114,
      164,
      225,
      266
    ],
    "Operating Profit": [
      26,
      29,
      51,
      86,
      118,
      155,
      160
    ],
    "OPM %": [
      19,
      20,
      34,
      43,
      42,
      41,
      38
    ],
    "Other Income\u00a0+": [
      28,
      15,
      40,
      42,
      34,
      38,
      42
    ],
    "Interest": [
      3,
      3,
      3,
      2,
      3,
      3,
      3
    ],
    "Depreciation": [
      9,
      10,
      10,
      8,
      10,
      15,
      20
    ],
    "Profit before tax": [
      42,
      32,
      79,
      117,
      139,
      175,
      179
    ],
    "Tax %": [
      20,
      27,
      24,
      26,
      23,
      23,
      0
    ],
    "Net Profit\u00a0+": [
      34,
      23,
      60,
      87,
      108,
      134,
      137
    ],
    "EPS in Rs": [
      87.59,
      60.53,
      156.07,
      16.34,
      19.99,
      24.77,
      25.18
    ],
    "Dividend Payout %": [
      0,
      0,
      0,
      12,
      25,
      14,
      0
    ]
  },
  "compounded_sales_growth": {
    "date": [
      "5 Years",
      "3 Years",
      "TTM",
      "Last Year"
    ],
    "Compounded Sales Growth": [
      20.0,
      20.0,
      24.0,
      21.0
    ]
  },
  "compounded_profit_growth": {
    "date": [
      "5 Years",
      "3 Years",
      "TTM",
      "Last Year"
    ],
    "Compounded Profit Growth": [
      20.0,
      20.0,
      24.0,
      21.0
    ]
  },
  "stock_price_cagr": {
    "date": [
      "5 Years",
      "3 Years",
      "TTM",
      "Last Year"
    ],
    "Stock Price Cagr": [
      20.0,
      20.0,
      24.0,
      21.0
    ]
  },
  "return_on_equity": {
    "date": [
      "5 Years",
      "3 Years",
      "TTM",
      "Last Year"
    ],
    "Return On Equity": [
      20.0,
      20.0,
      24.0,
      21.0
    ]
  },
  "balance_sheet": {
    "date": [
      "Mar 2019",
      "Mar 2020",
      "Mar 2021",
      "Mar 2022",
      "Mar 2023",
      "Mar 2024",
      "Sep 2024"
    ],
    "Equity Capital": [
      4,
      4,
      4,
      11,
      11,
      11,
      11
    ],
    "Reserves": [
      152,
      165,
      225,
      435,
      531,
      648,
      717
    ],
    "Borrowings\u00a0+": [
      154,
      151,
      149,
      19,
      29,
      26,
      35
    ],
    "Other Liabilities\u00a0+": [
      30,
      39,
      50,
      53,
      101,
      109,
      81
    ],
    "Total Liabilities": [
      340,
      358,
      428,
      518,
      673,
      794,
      843
    ],
    "Fixed Assets\u00a0+": [
      44,
      41,
      33,
      43,
      49,
      61,
      77
    ],
    "CWIP": [
      0,
      0,
      0,
      0,
      7,
      10,
      0
    ],
    "Investments": [
      201,
      199,
      269,
      296,
      362,
      409,
      446
    ],
    "Other Assets\u00a0+": [
      95,
      119,
      126,
      178,
      254,
      313,
      320
    ],
    "Total Assets": [
      340,
      358,
      428,
      518,
      673,
      794,
      843
    ]
  },
  "cash_flows": {
    "date": [
      "Mar 2019",
      "Mar 2020",
      "Mar 2021",
      "Mar 2022",
      "Mar 2023",
      "Mar 2024"
    ],
    "Debtor Days": [
      64,
      76,
      68,
      79,
      76,
      101
    ],
    "Inventory Days": [
      86,
      119,
      74,
      191,
      140,
      71
    ],
    "Days Payable": [
      82,
      152,
      99,
      120,
      99,
      144
    ],
    "Cash Conversion Cycle": [
      69,
      44,
      43,
      150,
      116,
      28
    ],
    "Working Capital Days": [
      32,
      38,
      3,
      70,
      25,
      55
    ],
    "ROCE %": [
      0,
      10,
      19,
      21,
      25,
      26
    ]
  },
  "ratios": {
    "date": [
      "Mar 2019",
      "Mar 2020",
      "Mar 2021",
      "Mar 2022",
      "Mar 2023",
      "Mar 2024"
    ],
    "Debtor Days": [
      64,
      76,
      68,
      79,
      76,
      101
    ],
    "Inventory Days": [
      86,
      119,
      74,
      191,
      140,
      71
    ],
    "Days Payable": [
      82,
      152,
      99,
      120,
      99,
      144
    ],
    "Cash Conversion Cycle": [
      69,
      44,
      43,
      150,
      116,
      28
    ],
    "Working Capital Days": [
      32,
      38,
      3,
      70,
      25,
      55
    ],
    "ROCE %": [
      0,
      10,
      19,
      21,
      25,
      26
    ]
  },
  "shareholding_pattern": {
    "date": [
      "Mar 2022",
      "Jun 2022",
      "Sep 2022",
      "Dec 2022",
      "Mar 2023",
      "Jun 2023",
      "Sep 2023",
      "Dec 2023",
      "Mar 2024",
      "Jun 2024",
      "Sep 2024",
      "Dec 2024"
    ],
    "Promoters\u00a0+": [
      53.73,
      53.73,
      53.31,
      53.31,
      53.31,
      53.31,
      52.93,
      52.91,
      52.91,
      51.98,
      51.67,
      51.67
    ],
    "FIIs\u00a0+": [
      5.57,
      5.6,
      5.57,
      5.5,
      6.61,
      4.02,
      5.74,
      5.98,
      6.73,
      6.41,
      6.44,
      4.66
    ],
    "DIIs\u00a0+": [
      4.8,
      5.26,
      5.07,
      4.41,
      4.85,
      6.93,
      5.79,
      4.29,
      4.73,
      5.76,
      5.76,
      7.14
    ],
    "Public\u00a0+": [
      35.9,
      35.41,
      36.05,
      36.79,
      35.22,
      35.74,
      35.53,
      36.82,
      35.64,
      35.85,
      36.14,
      36.54
    ],
    "No. of Shareholders": [
      151018,
      145219,
      153585,
      153333,
      146982,
      147248,
      135820,
      162163,
      155675,
      159382,
      162409,
      166270
    ]
  },
  "market_data": {
    "Market Cap": 9391,
    "Current Price": 1725,
    "High / Low": "2748 / 1513",
    "Stock P/E": 68.8,
    "Book Value": 134,
    "Dividend Yield": 0.2,
    "ROCE": 26.2,
    "ROE": 20.6,
    "Face Value": 2.0
  },
  "remarks": {
    "pros": [
      "Company is almost debt free.",
      "Company has delivered good profit growth of 44.0% CAGR over last 5 years",
      "Company has been maintaining a healthy dividend payout of 17.1%"
    ],
    "cons": [
      "Stock is trading at 12.9 times its book value"
    ]
  }
}