{
  "symbol": "MPHASIS",
  "url": "https://www.screener.in/company/MPHASIS/consolidated/",
  "timestamp": 1743776703.4789078,
  "quarterly_results": {
    "date": [
      "Dec 2021",
      "Mar 2022",
      "Jun 2022",
      "Sep 2022",
      "Dec 2022",
      "Mar 2023",
      "Jun 2023",
      "Sep 2023",
      "Dec 2023",
      "Mar 2024",
      "Jun 2024",
      "Sep 2024",
      "Dec 2024"
    ],
    "Sales\u00a0+": [
      3124,
      3278,
      3411,
      3520,
      3506,
      3361,
      3252,
      3276,
      3338,
      3412,
      3422,
      3536,
      3561
    ],
    "Expenses\u00a0+": [
      2571,
      2701,
      2811,
      2902,
      2889,
      2763,
      2665,
      2681,
      2737,
      2773,
      2804,
      2888,
      2883
    ],
    "Operating Profit": [
      553,
      577,
      600,
      618,
      618,
      599,
      587,
      596,
      601,
      639,
      619,
      648,
      678
    ],
    "OPM %": [
      18,
      18,
      18,
      18,
      18,
      18,
      18,
      18,
      18,
      19,
      18,
      18,
      19
    ],
    "Other Income\u00a0+": [
      31,
      39,
      36,
      43,
      40,
      43,
      50,
      49,
      54,
      64,
      74,
      59,
      63
    ],
    "Interest": [
      22,
      21,
      23,
      26,
      24,
      24,
      24,
      34,
      53,
      50,
      50,
      40,
      39
    ],
    "Depreciation": [
      83,
      80,
      80,
      80,
      82,
      83,
      87,
      89,
      103,
      131,
      105,
      104,
      132
    ],
    "Profit before tax": [
      480,
      516,
      533,
      555,
      551,
      534,
      526,
      522,
      499,
      522,
      537,
      563,
      569
    ],
    "Tax %": [
      25,
      24,
      25,
      25,
      25,
      24,
      25,
      25,
      25,
      25,
      25,
      25,
      25
    ],
    "Net Profit\u00a0+": [
      358,
      392,
      402,
      418,
      412,
      405,
      396,
      392,
      374,
      393,
      405,
      423,
      428
    ],
    "EPS in Rs": [
      19.08,
      20.88,
      21.37,
      22.24,
      21.89,
      21.51,
      21.01,
      20.78,
      19.79,
      20.81,
      21.39,
      22.37,
      22.56
    ],
    "Raw PDF": [
      0,
      0,
      0,
      0,
      0,
      0,
      0,
      0,
      0,
      0,
      0,
      0,
      0
    ]
  },
  "profit_loss": {
    "date": [
      "Oct 2013",
      "Mar 2014\n            \n              5m",
      "Mar 2015",
      "Mar 2016",
      "Mar 2017",
      "Mar 2018",
      "Mar 2019",
      "Mar 2020",
      "Mar 2021",
      "Mar 2022",
      "Mar 2023",
      "Mar 2024",
      "TTM"
    ],
    "Sales\u00a0+": [
      5796,
      2594,
      5795,
      6081,
      6076,
      6546,
      7731,
      8844,
      9722,
      11961,
      13798,
      13279,
      13932
    ],
    "Expenses\u00a0+": [
      4764,
      2154,
      4925,
      5218,
      5108,
      5483,
      6407,
      7193,
      7919,
      9844,
      11365,
      10857,
      11349
    ],
    "Operating Profit": [
      1033,
      440,
      870,
      863,
      969,
      1062,
      1324,
      1650,
      1803,
      2118,
      2434,
      2422,
      2583
    ],
    "OPM %": [
      18,
      17,
      15,
      14,
      16,
      16,
      17,
      19,
      19,
      18,
      18,
      18,
      19
    ],
    "Other Income\u00a0+": [
      140,
      44,
      194,
      172,
      223,
      149,
      177,
      178,
      133,
      160,
      162,
      218,
      259
    ],
    "Interest": [
      33,
      11,
      28,
      24,
      14,
      13,
      17,
      81,
      63,
      74,
      97,
      161,
      179
    ],
    "Depreciation": [
      145,
      50,
      98,
      121,
      79,
      71,
      76,
      232,
      242,
      291,
      325,
      410,
      472
    ],
    "Profit before tax": [
      995,
      422,
      938,
      890,
      1099,
      1128,
      1407,
      1515,
      1631,
      1913,
      2173,
      2068,
      2191
    ],
    "Tax %": [
      25,
      28,
      28,
      29,
      28,
      26,
      24,
      22,
      25,
      25,
      25,
      25,
      0
    ],
    "Net Profit\u00a0+": [
      744,
      303,
      675,
      632,
      792,
      838,
      1073,
      1185,
      1217,
      1431,
      1638,
      1555,
      1649
    ],
    "EPS in Rs": [
      35.4,
      14.4,
      32.1,
      30.05,
      37.62,
      43.34,
      57.64,
      63.52,
      65.06,
      76.19,
      86.94,
      82.27,
      87.13
    ],
    "Dividend Payout %": [
      48,
      49,
      50,
      67,
      45,
      46,
      47,
      55,
      100,
      60,
      58,
      67,
      0
    ]
  },
  "compounded_sales_growth": {
    "date": [
      "10 Years",
      "5 Years",
      "3 Years",
      "TTM",
      "Last Year"
    ],
    "Compounded Sales Growth": [
      18.0,
      20.0,
      20.0,
      5.0,
      18.0
    ]
  },
  "compounded_profit_growth": {
    "date": [
      "10 Years",
      "5 Years",
      "3 Years",
      "TTM",
      "Last Year"
    ],
    "Compounded Profit Growth": [
      18.0,
      20.0,
      20.0,
      5.0,
      18.0
    ]
  },
  "stock_price_cagr": {
    "date": [
      "10 Years",
      "5 Years",
      "3 Years",
      "TTM",
      "Last Year"
    ],
    "Stock Price Cagr": [
      18.0,
      20.0,
      20.0,
      5.0,
      18.0
    ]
  },
  "return_on_equity": {
    "date": [
      "10 Years",
      "5 Years",
      "3 Years",
      "TTM",
      "Last Year"
    ],
    "Return On Equity": [
      18.0,
      20.0,
      20.0,
      5.0,
      18.0
    ]
  },
  "balance_sheet": {
    "date": [
      "Oct 2013",
      "Mar 2014",
      "Mar 2015",
      "Mar 2016",
      "Mar 2017",
      "Mar 2018",
      "Mar 2019",
      "Mar 2020",
      "Mar 2021",
      "Mar 2022",
      "Mar 2023",
      "Mar 2024",
      "Sep 2024"
    ],
    "Equity Capital": [
      210,
      210,
      210,
      210,
      210,
      193,
      186,
      187,
      187,
      188,
      188,
      189,
      189
    ],
    "Reserves": [
      4724,
      4905,
      5270,
      5645,
      5942,
      5289,
      5064,
      5643,
      6340,
      6755,
      7746,
      8606,
      8480
    ],
    "Borrowings\u00a0+": [
      554,
      540,
      575,
      461,
      260,
      390,
      543,
      571,
      513,
      527,
      198,
      1544,
      1820
    ],
    "Other Liabilities\u00a0+": [
      1601,
      1320,
      1312,
      1092,
      889,
      1109,
      1576,
      2339,
      2324,
      3214,
      3373,
      3662,
      3092
    ],
    "Total Liabilities": [
      7090,
      6974,
      7367,
      7408,
      7301,
      6980,
      7368,
      8740,
      9365,
      10684,
      11506,
      14000,
      13582
    ],
    "Fixed Assets\u00a0+": [
      2462,
      2404,
      2334,
      1597,
      1921,
      1884,
      2170,
      3013,
      3020,
      3774,
      4060,
      5533,
      5558
    ],
    "CWIP": [
      26,
      6,
      20,
      56,
      1,
      2,
      3,
      17,
      3,
      11,
      32,
      61,
      0
    ],
    "Investments": [
      1899,
      1815,
      1443,
      2122,
      2396,
      1782,
      1329,
      1326,
      1846,
      1813,
      1753,
      3090,
      2123
    ],
    "Other Assets\u00a0+": [
      2702,
      2748,
      3569,
      3633,
      2983,
      3312,
      3866,
      4384,
      4496,
      5087,
      5662,
      5316,
      5901
    ],
    "Total Assets": [
      7090,
      6974,
      7367,
      7408,
      7301,
      6980,
      7368,
      8740,
      9365,
      10684,
      11506,
      14000,
      13582
    ]
  },
  "cash_flows": {
    "date": [
      "Oct 2013",
      "Mar 2014",
      "Mar 2015",
      "Mar 2016",
      "Mar 2017",
      "Mar 2018",
      "Mar 2019",
      "Mar 2020",
      "Mar 2021",
      "Mar 2022",
      "Mar 2023",
      "Mar 2024"
    ],
    "Debtor Days": [
      41,
      109,
      39,
      39,
      38,
      45,
      45,
      34,
      35,
      68,
      67,
      67
    ],
    "Inventory Days": [
      0,
      0,
      0,
      0,
      0,
      0,
      0,
      0,
      0,
      0,
      0,
      0
    ],
    "Days Payable": [
      0,
      0,
      0,
      0,
      0,
      0,
      0,
      0,
      0,
      0,
      0,
      0
    ],
    "Cash Conversion Cycle": [
      41,
      109,
      39,
      39,
      38,
      45,
      45,
      34,
      35,
      68,
      67,
      67
    ],
    "Working Capital Days": [
      -10,
      22,
      3,
      28,
      44,
      42,
      44,
      29,
      34,
      29,
      25,
      16
    ],
    "ROCE %": [
      20,
      8,
      16,
      15,
      18,
      19,
      24,
      26,
      25,
      27,
      29,
      24
    ]
  },
  "ratios": {
    "date": [
      "Oct 2013",
      "Mar 2014",
      "Mar 2015",
      "Mar 2016",
      "Mar 2017",
      "Mar 2018",
      "Mar 2019",
      "Mar 2020",
      "Mar 2021",
      "Mar 2022",
      "Mar 2023",
      "Mar 2024"
    ],
    "Debtor Days": [
      41,
      109,
      39,
      39,
      38,
      45,
      45,
      34,
      35,
      68,
      67,
      67
    ],
    "Inventory Days": [
      0,
      0,
      0,
      0,
      0,
      0,
      0,
      0,
      0,
      0,
      0,
      0
    ],
    "Days Payable": [
      0,
      0,
      0,
      0,
      0,
      0,
      0,
      0,
      0,
      0,
      0,
      0
    ],
    "Cash Conversion Cycle": [
      41,
      109,
      39,
      39,
      38,
      45,
      45,
      34,
      35,
      68,
      67,
      67
    ],
    "Working Capital Days": [
      -10,
      22,
      3,
      28,
      44,
      42,
      44,
      29,
      34,
      29,
      25,
      16
    ],
    "ROCE %": [
      20,
      8,
      16,
      15,
      18,
      19,
      24,
      26,
      25,
      27,
      29,
      24
    ]
  },
  "shareholding_pattern": {
    "date": [
      "Mar 2022",
      "Jun 2022",
      "Sep 2022",
      "Dec 2022",
      "Mar 2023",
      "Jun 2023",
      "Sep 2023",
      "Dec 2023",
      "Mar 2024",
      "Jun 2024",
      "Sep 2024",
      "Dec 2024"
    ],
    "Promoters\u00a0+": [
      55.8,
      55.72,
      55.7,
      55.65,
      55.63,
      55.58,
      55.57,
      55.52,
      55.45,
      40.35,
      40.32,
      40.23
    ],
    "FIIs\u00a0+": [
      21.09,
      20.48,
      20.71,
      18.89,
      17.72,
      17.19,
      16.6,
      15.72,
      14.84,
      18.32,
      18.25,
      20.78
    ],
    "DIIs\u00a0+": [
      18.04,
      18.16,
      17.78,
      19.54,
      21.0,
      21.05,
      22.55,
      23.71,
      24.63,
      35.84,
      36.87,
      34.62
    ],
    "Public\u00a0+": [
      5.07,
      5.64,
      5.8,
      5.93,
      5.65,
      6.19,
      5.27,
      5.06,
      5.08,
      5.49,
      4.54,
      4.38
    ],
    "Others\u00a0+": [
      0.0,
      0.0,
      0.0,
      0.0,
      0.0,
      0.0,
      0.0,
      0.0,
      0.01,
      0.0,
      0.03,
      0.0
    ],
    "No. of Shareholders": [
      126895,
      151470,
      177533,
      177456,
      169215,
      177013,
      153792,
      148428,
      147350,
      167593,
      149318,
      143700
    ]
  },
  "market_data": {
    "Market Cap": 42367,
    "Current Price": 2229,
    "High / Low": "3240 / 2170",
    "Stock P/E": 25.7,
    "Book Value": 457,
    "Dividend Yield": 2.47,
    "ROCE": 24.0,
    "ROE": 18.4,
    "Face Value": 10.0
  },
  "remarks": {
    "pros": [
      "Company has been maintaining a healthy dividend payout of 61.6%",
      "Company's working capital requirements have reduced from 23.0 days to 15.5 days"
    ],
    "cons": [
      "The company has delivered a poor sales growth of 11.4% over past five years.",
      "Promoter holding has decreased over last 3 years: -15.7%"
    ]
  }
}