{
  "symbol": "TATATECH",
  "url": "https://www.screener.in/company/TATATECH/consolidated/",
  "timestamp": 1743779955.866451,
  "quarterly_results": {
    "date": [
      "Dec 2022",
      "Mar 2023",
      "Jun 2023",
      "Sep 2023",
      "Dec 2023",
      "Mar 2024",
      "Jun 2024",
      "Sep 2024",
      "Dec 2024"
    ],
    "Sales\u00a0+": [
      1124,
      1402,
      1258,
      1269,
      1289,
      1301,
      1269,
      1296,
      1317
    ],
    "Expenses\u00a0+": [
      918,
      1160,
      1007,
      1055,
      1053,
      1061,
      1038,
      1061,
      1083
    ],
    "Operating Profit": [
      206,
      243,
      250,
      214,
      237,
      240,
      231,
      236,
      234
    ],
    "OPM %": [
      18,
      17,
      20,
      17,
      18,
      18,
      18,
      18,
      18
    ],
    "Other Income\u00a0+": [
      18,
      47,
      31,
      30,
      31,
      24,
      23,
      16,
      28
    ],
    "Interest": [
      5,
      5,
      5,
      5,
      5,
      4,
      5,
      5,
      6
    ],
    "Depreciation": [
      24,
      25,
      24,
      26,
      27,
      29,
      30,
      30,
      30
    ],
    "Profit before tax": [
      194,
      260,
      253,
      213,
      235,
      231,
      220,
      217,
      226
    ],
    "Tax %": [
      24,
      17,
      24,
      25,
      28,
      32,
      26,
      28,
      25
    ],
    "Net Profit\u00a0+": [
      148,
      217,
      192,
      160,
      170,
      157,
      162,
      157,
      169
    ],
    "EPS in Rs": [
      36.58,
      5.34,
      4.72,
      3.95,
      4.2,
      3.88,
      3.99,
      3.88,
      4.16
    ],
    "Raw PDF": [
      0,
      0,
      0,
      0,
      0,
      0,
      0,
      0,
      0
    ]
  },
  "profit_loss": {
    "date": [
      "Mar 2019",
      "Mar 2020",
      "Mar 2021",
      "Mar 2022",
      "Mar 2023",
      "Mar 2024",
      "TTM"
    ],
    "Sales\u00a0+": [
      2942,
      2852,
      2381,
      3530,
      4414,
      5117,
      5184
    ],
    "Expenses\u00a0+": [
      2437,
      2382,
      1995,
      2884,
      3593,
      4176,
      4243
    ],
    "Operating Profit": [
      505,
      470,
      386,
      646,
      821,
      941,
      941
    ],
    "OPM %": [
      17,
      16,
      16,
      18,
      19,
      18,
      18
    ],
    "Other Income\u00a0+": [
      36,
      36,
      39,
      49,
      88,
      116,
      92
    ],
    "Interest": [
      1,
      16,
      18,
      22,
      18,
      19,
      19
    ],
    "Depreciation": [
      69,
      99,
      92,
      86,
      95,
      106,
      119
    ],
    "Profit before tax": [
      471,
      392,
      315,
      587,
      796,
      932,
      894
    ],
    "Tax %": [
      25,
      36,
      24,
      26,
      22,
      27,
      0
    ],
    "Net Profit\u00a0+": [
      353,
      252,
      239,
      437,
      624,
      679,
      645
    ],
    "EPS in Rs": [
      0,
      0,
      0,
      0,
      15.38,
      16.75,
      15.91
    ],
    "Dividend Payout %": [
      18,
      66,
      0,
      0,
      80,
      60,
      0
    ]
  },
  "compounded_sales_growth": {
    "date": [
      "5 Years",
      "3 Years",
      "Last Year"
    ],
    "Compounded Sales Growth": [
      19.0,
      22.0,
      22.0
    ]
  },
  "compounded_profit_growth": {
    "date": [
      "5 Years",
      "3 Years",
      "Last Year"
    ],
    "Compounded Profit Growth": [
      19.0,
      22.0,
      22.0
    ]
  },
  "stock_price_cagr": {
    "date": [
      "5 Years",
      "3 Years",
      "Last Year"
    ],
    "Stock Price Cagr": [
      19.0,
      22.0,
      22.0
    ]
  },
  "return_on_equity": {
    "date": [
      "5 Years",
      "3 Years",
      "Last Year"
    ],
    "Return On Equity": [
      19.0,
      22.0,
      22.0
    ]
  },
  "balance_sheet": {
    "date": [
      "Mar 2019",
      "Mar 2020",
      "Mar 2021",
      "Mar 2022",
      "Mar 2023",
      "Mar 2024",
      "Sep 2024"
    ],
    "Equity Capital": [
      42,
      42,
      42,
      42,
      81,
      81,
      81
    ],
    "Reserves": [
      1715,
      1811,
      2100,
      2238,
      2908,
      3140,
      3134
    ],
    "Borrowings\u00a0+": [
      0,
      258,
      266,
      261,
      255,
      257,
      260
    ],
    "Other Liabilities\u00a0+": [
      512,
      462,
      1164,
      1676,
      1957,
      2100,
      2392
    ],
    "Total Liabilities": [
      2269,
      2573,
      3573,
      4218,
      5201,
      5578,
      5867
    ],
    "Fixed Assets\u00a0+": [
      819,
      1119,
      1090,
      1068,
      1095,
      1151,
      1165
    ],
    "CWIP": [
      25,
      0,
      0,
      0,
      3,
      0,
      0
    ],
    "Investments": [
      39,
      36,
      497,
      528,
      30,
      150,
      185
    ],
    "Other Assets\u00a0+": [
      1386,
      1417,
      1986,
      2622,
      4074,
      4277,
      4517
    ],
    "Total Assets": [
      2269,
      2573,
      3573,
      4218,
      5201,
      5578,
      5867
    ]
  },
  "cash_flows": {
    "date": [
      "Mar 2019",
      "Mar 2020",
      "Mar 2021",
      "Mar 2022",
      "Mar 2023",
      "Mar 2024"
    ],
    "Debtor Days": [
      71,
      93,
      91,
      79,
      91,
      82
    ],
    "Inventory Days": [
      0,
      0,
      0,
      0,
      0,
      0
    ],
    "Days Payable": [
      312,
      0,
      0,
      0,
      0,
      0
    ],
    "Cash Conversion Cycle": [
      -241,
      93,
      91,
      79,
      91,
      82
    ],
    "Working Capital Days": [
      55,
      65,
      -6,
      -8,
      69,
      60
    ],
    "ROCE %": [
      0,
      22,
      15,
      25,
      28,
      28
    ]
  },
  "ratios": {
    "date": [
      "Mar 2019",
      "Mar 2020",
      "Mar 2021",
      "Mar 2022",
      "Mar 2023",
      "Mar 2024"
    ],
    "Debtor Days": [
      71,
      93,
      91,
      79,
      91,
      82
    ],
    "Inventory Days": [
      0,
      0,
      0,
      0,
      0,
      0
    ],
    "Days Payable": [
      312,
      0,
      0,
      0,
      0,
      0
    ],
    "Cash Conversion Cycle": [
      -241,
      93,
      91,
      79,
      91,
      82
    ],
    "Working Capital Days": [
      55,
      65,
      -6,
      -8,
      69,
      60
    ],
    "ROCE %": [
      0,
      22,
      15,
      25,
      28,
      28
    ]
  },
  "shareholding_pattern": {
    "date": [
      "Dec 2023",
      "Mar 2024",
      "Jun 2024",
      "Sep 2024",
      "Dec 2024"
    ],
    "Promoters\u00a0+": [
      55.39,
      55.39,
      55.39,
      55.22,
      55.22
    ],
    "FIIs\u00a0+": [
      2.02,
      1.1,
      1.63,
      3.62,
      3.1
    ],
    "DIIs\u00a0+": [
      2.5,
      1.51,
      1.78,
      3.44,
      3.06
    ],
    "Public\u00a0+": [
      40.09,
      42.01,
      41.2,
      37.72,
      38.61
    ],
    "No. of Shareholders": [
      1039672,
      1178338,
      1241881,
      1279750,
      1350826
    ]
  },
  "market_data": {
    "Market Cap": 26312,
    "Current Price": 649,
    "High / Low": "1138 / 627",
    "Stock P/E": 40.8,
    "Book Value": 79.2,
    "Dividend Yield": 1.29,
    "ROCE": 28.3,
    "ROE": 21.9,
    "Face Value": 2.0
  },
  "remarks": {
    "pros": [
      "Company is almost debt free.",
      "Company has been maintaining a healthy dividend payout of 46.6%"
    ],
    "cons": [
      "Stock is trading at 8.19 times its book value"
    ]
  }
}